Products.Formulator-2.1-py3.8-nspkg.pth
Products/Formulator/DummyField.py
Products/Formulator/EmailLinesField.py
Products/Formulator/Errors.py
Products/Formulator/FSForm.py
Products/Formulator/Field.py
Products/Formulator/FieldRegistry.py
Products/Formulator/Form.py
Products/Formulator/FormToXML.py
Products/Formulator/FormulatorFormFile.py
Products/Formulator/HelperFields.py
Products/Formulator/INSTALL.txt
Products/Formulator/InterfaceField.py
Products/Formulator/ListTextAreaField.py
Products/Formulator/MethodField.py
Products/Formulator/PatternChecker.py
Products/Formulator/ProductForm.py
Products/Formulator/StandardFields.py
Products/Formulator/TALESField.py
Products/Formulator/Validator.py
Products/Formulator/Widget.py
Products/Formulator/XMLObjects.py
Products/Formulator/XMLToForm.py
Products/Formulator/__init__.py
Products/Formulator/configure.zcml
Products/Formulator/ftesting.zcml
Products/Formulator/helpers.py
Products/Formulator/homepage.html
Products/Formulator/interfaces.py
Products/Formulator/monkey.py
Products/Formulator/testing.py
Products/Formulator/zeamsupport.py
Products/Formulator/dtml/fieldAdd.dtml
Products/Formulator/dtml/fieldEdit.dtml
Products/Formulator/dtml/fieldListHeader.dtml
Products/Formulator/dtml/fieldMessages.dtml
Products/Formulator/dtml/fieldOverride.dtml
Products/Formulator/dtml/fieldTales.dtml
Products/Formulator/dtml/fieldTest.dtml
Products/Formulator/dtml/formAdd.dtml
Products/Formulator/dtml/formOrder.dtml
Products/Formulator/dtml/formSettings.dtml
Products/Formulator/dtml/formTest.dtml
Products/Formulator/dtml/formXML.dtml
Products/Formulator/help/BasicForm.py
Products/Formulator/help/Field.py
Products/Formulator/help/Form.py
Products/Formulator/help/ZMIForm.py
Products/Formulator/help/dogfood.txt
Products/Formulator/help/fieldEdit.txt
Products/Formulator/help/fieldMessages.txt
Products/Formulator/help/fieldOverride.txt
Products/Formulator/help/fieldTales.txt
Products/Formulator/help/fieldTest.txt
Products.Formulator-2.1.dist-info/LICENSE.txt
Products.Formulator-2.1.dist-info/METADATA
Products.Formulator-2.1.dist-info/WHEEL
Products.Formulator-2.1.dist-info/namespace_packages.txt
Products.Formulator-2.1.dist-info/top_level.txt
Products.Formulator-2.1.dist-info/RECORD
