Metadata-Version: 2.1
Name: Products.Formulator
Version: 2.1
Summary: Form library for Zope 4
Home-page: https://github.com/infrae/Products.Formulator
Author: Martijn Faassen and community
Author-email: info@infrae.com
License: BSD
Keywords: form generator zope4
Platform: UNKNOWN
Classifier: Development Status :: 5 - Production/Stable
Classifier: Framework :: Zope :: 4
Classifier: License :: OSI Approved :: BSD License
Classifier: Programming Language :: Python
Classifier: Programming Language :: Python :: 2.7
Classifier: Programming Language :: Python :: 3.7
Classifier: Programming Language :: Python :: 3.8
Classifier: Programming Language :: Python :: 3.9
Classifier: Programming Language :: Python :: 3.10
Classifier: Programming Language :: Python :: 3.11
Classifier: Topic :: Software Development :: Libraries :: Python Modules
License-File: LICENSE.txt
Requires-Dist: AccessControl
Requires-Dist: DocumentTemplate
Requires-Dist: grokcore.component
Requires-Dist: setuptools
Requires-Dist: six
Requires-Dist: zope.component
Requires-Dist: zope.i18nmessageid
Requires-Dist: zope.interface
Requires-Dist: zope.cachedescriptors
Requires-Dist: zeam.form.base
Requires-Dist: grokcore.chameleon (<4.0) ; python_version == "2.7"
Requires-Dist: DocumentTemplate (<4.0) ; python_version == "2.7"
Requires-Dist: grokcore.component (<4.0) ; python_version == "2.7"
Requires-Dist: grokcore.view (<4.0) ; python_version == "2.7"
Requires-Dist: martian (<2.0) ; python_version == "2.7"
Requires-Dist: zeam.form.base (<1.4) ; python_version == "2.7"
Provides-Extra: test
Requires-Dist: Products.PythonScripts ; extra == 'test'
Requires-Dist: plone.testing ; extra == 'test'
Requires-Dist: Products.PythonScripts (<5.0) ; (python_version == "2.7") and extra == 'test'
